lambda_middleware/__init__.py
lambda_middleware/config.py
lambda_middleware/middleware.py
lambda_middleware/cli/functions.py
lambda_middleware/cli/main.py
lambda_middleware-0.3.1.dist-info/METADATA
lambda_middleware-0.3.1.dist-info/WHEEL
lambda_middleware-0.3.1.dist-info/entry_points.txt
lambda_middleware-0.3.1.dist-info/RECORD
