Metadata-Version: 2.4
Name: lambda-middleware
Version: 0.3.1
Summary: Python client for AWS Lambda middleware functions
Requires-Python: >=3.13
Requires-Dist: boto3>=1.40.39
Requires-Dist: click>=8.3.0
Requires-Dist: pydantic-settings>=2.11.0
Requires-Dist: pydantic>=2.11.9
Requires-Dist: ruff>=0.13.2
